Metadata-Version: 2.4
Name: hype-tools
Version: 0.1.4
Summary: A collection of tools for analyzing HYPe reads
Author-email: Luisa Kalkert <luisa.kalkert@gmx.de>
License-File: LICENSE
Requires-Dist: click
Requires-Dist: numpy
Requires-Dist: pandas
Requires-Dist: tqdm
Requires-Dist: biopython
Requires-Dist: python-Levenshtein
Requires-Dist: minineedle
Requires-Dist: scipy
Requires-Dist: statistics
Dynamic: license-file
